shopify_app/__init__.py
shopify_app/apps.py
shopify_app/decorators.py
shopify_app/exceptions.py
shopify_app/middleware.py
shopify_app/models.py
shopify_app/urls.py
shopify_app/views.py
shopify_app/management/__init__.py
shopify_app/management/commands/__init__.py
shopify_app/management/commands/activate_shop_webhooks.py
shopify_app/migrations/__init__.py
shopify_app/services/__init__.py
shopify_app/services/webhooks.py
shopify_app/templates/__init__.py
shopify_app/templates/shopify_app/__init__.py
shopify_app/templates/shopify_app/index.html
shopify_app/test/__init__.py
shopify_app/utils/__init__.py
django_shopify_app-2.0.23.dist-info/METADATA
django_shopify_app-2.0.23.dist-info/WHEEL
django_shopify_app-2.0.23.dist-info/top_level.txt
django_shopify_app-2.0.23.dist-info/RECORD
