Metadata-Version: 2.4
Name: django_shopify_app
Version: 2.0.23
Summary: A django app with all the tools required to make a Shopify app
Home-page: http://pypi.python.org/pypi/django_shopify_app/
Author: Santiago Fernandez
Author-email: 
License: MIT
Requires-Dist: Django>=4.0.0
Requires-Dist: pytest
Requires-Dist: shopifyapi>=12.7.0
Requires-Dist: django-crm-events
Dynamic: author
Dynamic: description
Dynamic: description-content-type
Dynamic: home-page
Dynamic: license
Dynamic: requires-dist
Dynamic: summary
